anystack/__init__.py
anystack/auth/__init__.py
anystack/auth/base.py
anystack/auth/jwt_provider.py
anystack/auth/oauth/__init__.py
anystack/auth/oauth/base.py
anystack/auth/oauth/generic.py
anystack/auth/oauth/github.py
anystack/auth/oauth/logto.py
anystack/auth/oauth/openxlab.py
anystack/auth/oauth/provider.py
anystack/db/__init__.py
anystack/db/base.py
anystack/db/d1.py
anystack/db/sqlalchemy.py
anystack/gateway/__init__.py
anystack/gateway/base.py
anystack/gateway/starlette_impl.py
anystack/kv/__init__.py
anystack/kv/base.py
anystack/kv/cloudflare_kv.py
anystack/kv/memory.py
anystack/kv/models.py
anystack/kv/postgresql.py
anystack/kv/redis.py
anystack/migration/__init__.py
anystack/migration/base.py
anystack/migration/db.py
anystack/protocol/__init__.py
anystack/protocol/app.py
anystack/protocol/auth.py
anystack/protocol/cron.py
anystack/protocol/db.py
anystack/protocol/gateway.py
anystack/protocol/kv.py
anystack/protocol/migration.py
anystack/protocol/queue.py
anystack/protocol/realtime.py
anystack/protocol/scheduler.py
anystack/protocol/storage.py
anystack/queue/__init__.py
anystack/queue/asyncio_queue.py
anystack/queue/base.py
anystack/queue/cloudflare_queue.py
anystack/queue/db_queue.py
anystack/queue/pgmq_queue.py
anystack/realtime/__init__.py
anystack/realtime/base.py
anystack/realtime/supabase.py
anystack/realtime/distributed/__init__.py
anystack/realtime/distributed/distributed.py
anystack/realtime/distributed/models.py
anystack/realtime/distributed/server.py
anystack/scheduler/__init__.py
anystack/scheduler/base.py
anystack/scheduler/distributed/__init__.py
anystack/scheduler/distributed/distributed.py
anystack/scheduler/distributed/server.py
anystack/scheduler/distributed/worker.py
anystack/scheduler/single/__init__.py
anystack/scheduler/single/single.py
anystack/scheduler/single/worker.py
anystack/storage/__init__.py
anystack/storage/base.py
anystack/storage/opendal.py
anystack-0.1.5.dist-info/METADATA
anystack-0.1.5.dist-info/WHEEL
anystack-0.1.5.dist-info/RECORD
