Metadata-Version: 2.4
Name: anystack
Version: 0.1.5
Summary: 面向云原生应用的 Python 资源抽象层，提供统一的异步协议包装数据库、消息队列、对象存储、KV、调度器等基础设施能力
Project-URL: Homepage, https://github.com/LaciaProject/anystack
Project-URL: Documentation, https://github.com/LaciaProject/anystack#readme
Project-URL: Repository, https://github.com/LaciaProject/anystack
Project-URL: Issues, https://github.com/LaciaProject/anystack/issues
Project-URL: Changelog, https://github.com/LaciaProject/anystack/releases
Author-email: LaciaProject <luxuncang@qq.com>
Maintainer-email: LaciaProject <luxuncang@qq.com>
License: MIT
Keywords: abstraction,async,cloud-native,database,gateway,infrastructure,kv,queue,realtime,scheduler,storage
Classifier: Development Status :: 3 - Alpha
Classifier: Framework :: AsyncIO
Classifier: Intended Audience :: Developers
Classifier: License :: OSI Approved :: MIT License
Classifier: Operating System :: OS Independent
Classifier: Programming Language :: Python :: 3
Classifier: Programming Language :: Python :: 3 :: Only
Classifier: Programming Language :: Python :: 3.12
Classifier: Topic :: Database
Classifier: Topic :: Software Development :: Libraries :: Python Modules
Classifier: Topic :: System :: Distributed Computing
Requires-Python: >=3.12
Requires-Dist: aiohttp>=3.12.15
Requires-Dist: aiosqlite>=0.20.0
Requires-Dist: asyncpg>=0.30.0
Requires-Dist: authlib>=1.6.4
Requires-Dist: croniter>=6.0.0
Requires-Dist: greenlet>=3.2.4
Requires-Dist: httpx>=0.28.1
Requires-Dist: itsdangerous>=2.2.0
Requires-Dist: opendal>=0.46.0
Requires-Dist: pydantic>=2.11.7
Requires-Dist: redis>=6.4.0
Requires-Dist: rsa>=4.9.1
Requires-Dist: socksio>=1.0.0
Requires-Dist: sqlalchemy>=2.0.43
Requires-Dist: starlette>=0.48.0
Requires-Dist: supabase>=2.20.0
Requires-Dist: uvicorn>=0.37.0
